{
   "broker" : {
      "port" : 9998,
      "logFile" : "",
      "username" : "xxx",
      "host" : "0.0.0.0",
      "trace" : false,
      "pidFile" : "",
      "password" : "yyy",
      "debug" : true
   },
   "rabbitmq" : {
      "catalog" : "",
      "zones" : [
         {
            "mgmtPort" : 15672,
            "name" : "dc1",
            "port" : 5672,
            "mgmtPass" : "xxx",
            "host" : "xxx.xxx.xxx.xxx",
            "trace" : false,
            "mgmtHost" : "xxx.xxx.xxx.xxx",
            "mgmtUser" : "xxx"
         },
         {
            "mgmtPort" : 15672,
            "name" : "dc2",
            "port" : 5672,
            "mgmtPass" : "yyy",
            "host" : "yyy.yyy.yyy.yyy",
            "trace" : false,
            "mgmtHost" : "yyy.yyy.yyy.yyy",
            "mgmtUser" : "yyy"
         }
      ]
   }
}
